pdfsearcher/__init__.py
pdfsearcher/search.py
find_in_pdf-0.2.2.dist-info/LICENSE
find_in_pdf-0.2.2.dist-info/METADATA
find_in_pdf-0.2.2.dist-info/WHEEL
find_in_pdf-0.2.2.dist-info/entry_points.txt
find_in_pdf-0.2.2.dist-info/top_level.txt
find_in_pdf-0.2.2.dist-info/RECORD
