Metadata-Version: 2.2
Name: find-in-pdf
Version: 0.2.2
Summary: A simple tool to search for strings or list PDF files within a directory.
Home-page: https://github.com/anitejngo/pdfsearcher
Author: Ognjen Lazic
Author-email: laogdo@gmail.com
Classifier: Programming Language :: Python :: 3
Classifier: License :: OSI Approved :: MIT License
Classifier: Operating System :: OS Independent
Requires-Python: >=3.6
License-File: LICENSE
Requires-Dist: pdfplumber>=0.11.4
Dynamic: author
Dynamic: author-email
Dynamic: classifier
Dynamic: description
Dynamic: description-content-type
Dynamic: home-page
Dynamic: requires-dist
Dynamic: requires-python
Dynamic: summary
